MANIFEST.in
README.rst
setup.py
ssl_opt_out.pth
ssl_opt_out.py
ssl_opt_out.egg-info/PKG-INFO
ssl_opt_out.egg-info/SOURCES.txt
ssl_opt_out.egg-info/dependency_links.txt
ssl_opt_out.egg-info/not-zip-safe
ssl_opt_out.egg-info/top_level.txt