Metadata-Version: 1.1
Name: ssl-opt-out
Version: 0.9.0
Summary: Opt-out of Python SSL certificate verification.
Home-page: https://github.com/cchurch/ssl-opt-out
Author: Chris Church
Author-email: chris@ninemoreminutes.com
License: BSD
Keywords: python ssl
Platform: UNKNOWN
Classifier: Development Status :: 4 - Beta
Classifier: Intended Audience :: Developers
Classifier: License :: OSI Approved :: BSD License
Classifier: Operating System :: OS Independent
Classifier: Programming Language :: Python
Classifier: Programming Language :: Python :: 2.6
Classifier: Programming Language :: Python :: 2.7
Classifier: Programming Language :: Python :: 3.2
Classifier: Programming Language :: Python :: 3.3
Classifier: Programming Language :: Python :: 3.4
Classifier: Topic :: Software Development :: Libraries
